pyasl/__init__.py
pyasl/configs/__init__.py
pyasl/configs/mixed.yaml
pyasl/configs/testasltbx.yaml
pyasl/configs/testdlasl.yaml
pyasl/configs/testmricloud.yaml
pyasl/configs/testmti.yaml
pyasl/configs/testoxford.yaml
pyasl/configs/testpcasl.yaml
pyasl/models/model_068.hdf5
pyasl/models/model_099.hdf5
pyasl/modules/__init__.py
pyasl/modules/asltbx_coregister.py
pyasl/modules/asltbx_create_mask.py
pyasl/modules/asltbx_perfusion_quantify.py
pyasl/modules/asltbx_realign.py
pyasl/modules/asltbx_reset_orientation.py
pyasl/modules/asltbx_smooth.py
pyasl/modules/dlasl_build_mask.py
pyasl/modules/dlasl_denoise_cbf.py
pyasl/modules/mricloud_calculate_CBF.py
pyasl/modules/mricloud_calculate_M0.py
pyasl/modules/mricloud_calculate_diffmap.py
pyasl/modules/mricloud_coreg_mpr.py
pyasl/modules/mricloud_multidelay_calculate_CBFATT.py
pyasl/modules/mricloud_multidelay_calculate_M0.py
pyasl/modules/mricloud_read_mpr.py
pyasl/modules/mricloud_rescale.py
pyasl/modules/mricloud_t1roi_CBFaverage.py
pyasl/modules/oxford_asl_run.py
pyasl/modules/oxford_asl_split_m0.py
pyasl/modules/preclinical_abs_t1fit.py
pyasl/modules/preclinical_brain_mask.py
pyasl/modules/preclinical_cbf_relative.py
pyasl/modules/preclinical_compute_m0.py
pyasl/modules/preclinical_control_label_split.py
pyasl/modules/preclinical_diff_image.py
pyasl/modules/preclinical_loader_bruker.py
pyasl/modules/preclinical_loader_nifti.py
pyasl/modules/preclinical_motion_check.py
pyasl/modules/preclinical_slice_pld_adjust.py
pyasl/modules/preclinical_steady_state_trim.py
pyasl/modules/save_outputs.py
pyasl/pipelines/__init__.py
pyasl/pipelines/asl_mricloud_pipeline.py
pyasl/pipelines/asltbx_pipeline.py
pyasl/pipelines/custom_pipeline.py
pyasl/pipelines/dlasl_pipeline.py
pyasl/pipelines/oxford_asl_pipeline.py
pyasl/pipelines/preclinical_mti_pipeline.py
pyasl/pipelines/preclinical_pcasl_pipeline.py
pyasl/pipelines/run_pipeline.py
pyasl/tpm/TPM.nii
pyasl/utils/__init__.py
pyasl/utils/bruker_io.py
pyasl/utils/data_import.py
pyasl_osipi-0.2.1.dist-info/licenses/LICENSE
pyasl_osipi-0.2.1.dist-info/METADATA
pyasl_osipi-0.2.1.dist-info/WHEEL
pyasl_osipi-0.2.1.dist-info/top_level.txt
pyasl_osipi-0.2.1.dist-info/RECORD
