Metadata-Version: 2.4
Name: pyasl-osipi
Version: 0.2.1
Summary: A composite, open-source Python library for processing human and preclinical ASL MRI data.
Author-email: "tongxin (elo) li, OSIPI" <li.tongxin.elo@gmail.com>
License: MIT License
Project-URL: Homepage, https://github.com/elooff/PyASL
Classifier: Programming Language :: Python :: 3
Classifier: License :: OSI Approved :: MIT License
Classifier: Operating System :: OS Independent
Requires-Python: >=3.6
License-File: LICENSE
Requires-Dist: numpy>=1.20
Requires-Dist: nibabel>=3.2.0
Requires-Dist: nipype>=1.5.1
Requires-Dist: scipy>=1.7.0
Requires-Dist: scikit-image>=0.19.0
Requires-Dist: pandas>=1.5.0
Requires-Dist: tensorflow>=2.10
Requires-Dist: matplotlib>=3.5
Requires-Dist: pyyaml>=6.0
Requires-Dist: fsspec>=2022.5.0
Requires-Dist: jinja2>=3.0
Requires-Dist: typing-extensions>=4.8.0
Provides-Extra: macos
Requires-Dist: tensorflow-macos>=2.12; extra == "macos"
Requires-Dist: tensorflow-metal>=1.0; extra == "macos"
Provides-Extra: cpu
Requires-Dist: tensorflow>=2.12; extra == "cpu"
Provides-Extra: gpu
Requires-Dist: tensorflow>=2.14; extra == "gpu"
Provides-Extra: dev
Requires-Dist: pytest; extra == "dev"
Requires-Dist: ruff; extra == "dev"
Requires-Dist: black; extra == "dev"
Dynamic: license-file
